{"stats":{"minecraft:custom":{"minecraft:time_since_rest":1550,"minecraft:deaths":1,"minecraft:sprint_one_cm":6628,"minecraft:play_time":9737,"minecraft:damage_taken":237,"minecraft:walk_one_cm":6802,"minecraft:sneak_time":47,"minecraft:walk_under_water_one_cm":2663,"minecraft:drop":2,"minecraft:jump":85,"minecraft:damage_dealt":223,"minecraft:time_since_death":1522,"minecraft:leave_game":2,"minecraft:walk_on_water_one_cm":1421,"minecraft:climb_one_cm":145,"minecraft:total_world_time":9737,"minecraft:swim_one_cm":14151,"minecraft:interact_with_crafting_table":1,"minecraft:fall_one_cm":2473,"minecraft:fly_one_cm":11845},"minecraft:crafted":{"minecraft:oak_planks":32,"minecraft:crafting_table":1,"minecraft:wooden_axe":1},"minecraft:killed_by":{"minecraft:player":1},"minecraft:used":{"minecraft:crafting_table":1,"minecraft:oak_sapling":3},"minecraft:mined":{"minecraft:oak_log":9,"minecraft:oak_leaves":3},"minecraft:dropped":{"minecraft:oak_sapling":2},"minecraft:picked_up":{"minecraft:stick":2,"minecraft:oak_log":10,"minecraft:oak_sapling":5,"minecraft:oak_planks":25}},"DataVersion":4082}